sandlercorrespondingstates/__init__.py
sandlercorrespondingstates/charts.py
sandlercorrespondingstates/cli.py
sandlercorrespondingstates/data/Hdep_vs_Pr_isotherms.json
sandlercorrespondingstates/data/Sdep_vs_Pr_isotherms.json
sandlercorrespondingstates/data/Z_vs_Pr_indicials.json
sandlercorrespondingstates/data/Z_vs_Pr_isotherms.json
sandlercorrespondingstates-0.4.1.dist-info/METADATA
sandlercorrespondingstates-0.4.1.dist-info/WHEEL
sandlercorrespondingstates-0.4.1.dist-info/entry_points.txt
sandlercorrespondingstates-0.4.1.dist-info/licenses/LICENSE
sandlercorrespondingstates-0.4.1.dist-info/RECORD
